paranoid_logy/__init__.py
paranoid_logy/logy.py
paranoid_logy/logyservicecontext.py
paranoid_logy/traceresult.py
paranoid_logy-2.0.2.dist-info/LICENSE.md
paranoid_logy-2.0.2.dist-info/METADATA
paranoid_logy-2.0.2.dist-info/WHEEL
paranoid_logy-2.0.2.dist-info/top_level.txt
paranoid_logy-2.0.2.dist-info/RECORD
